privex/__init__.py
privex/eos/__init__.py
privex/eos/adapters.py
privex/eos/lib.py
privex/eos/node.py
privex/eos/objects.py
privex_eos-0.6.0.dist-info/LICENSE
privex_eos-0.6.0.dist-info/METADATA
privex_eos-0.6.0.dist-info/WHEEL
privex_eos-0.6.0.dist-info/top_level.txt
privex_eos-0.6.0.dist-info/RECORD
