Metadata-Version: 2.1
Name: privex-eos
Version: 0.6.0
Summary: EOS Python API by Privex Inc
Home-page: https://github.com/Privex/eos-python
Author: Chris (Someguy123) @ Privex
Author-email: chris@privex.io
License: MIT
Platform: UNKNOWN
Classifier: Programming Language :: Python :: 3
Classifier: Programming Language :: Python :: 3.6
Classifier: Programming Language :: Python :: 3.7
Classifier: Programming Language :: Python :: 3.8
Classifier: License :: OSI Approved :: MIT License
Classifier: Operating System :: OS Independent
Requires-Dist: httpx (>=0.8.0)
Requires-Dist: attrs
Requires-Dist: privex-helpers (>=2.6.0)
Requires-Dist: privex-coinhandlers
Requires-Dist: privex-db (>=0.9.1)
